{"detections": [{"start_time": 4.0, "end_time": 7.0, "name": "Engine", "confidence": 0.32}, {"start_time": 4.5, "end_time": 7.0, "name": "Aircraft", "confidence": 0.6}, {"start_time": 5.5, "end_time": 12.5, "name": "Vehicle", "confidence": 0.81}, {"start_time": 14.5, "end_time": 20.5, "name": "Vehicle", "confidence": 0.78}, {"start_time": 15.5, "end_time": 18.0, "name": "Aircraft", "confidence": 0.5}, {"start_time": 16.0, "end_time": 18.0, "name": "Fixed-wing_aircraft_and_airplane", "confidence": 0.3}], "num_detections": 6, "detected_classes": ["Fixed-wing_aircraft_and_airplane", "Vehicle", "Aircraft", "Engine"]}