{"detections": [{"start_time": 0.0, "end_time": 9.5, "name": "Mallet_percussion", "confidence": 0.91}, {"start_time": 0.0, "end_time": 1.0, "name": "Marimba_and_xylophone", "confidence": 0.68}, {"start_time": 0.0, "end_time": 1.0, "name": "Percussion", "confidence": 0.83}, {"start_time": 3.0, "end_time": 3.5, "name": "Marimba_and_xylophone", "confidence": 0.66}, {"start_time": 8.0, "end_time": 9.5, "name": "Marimba_and_xylophone", "confidence": 0.75}], "num_detections": 5, "detected_classes": ["Percussion", "Mallet_percussion", "Marimba_and_xylophone"]}