{"detections": [{"start_time": 0.0, "end_time": 15.0, "name": "Crowd", "confidence": 0.46}, {"start_time": 2.0, "end_time": 10.5, "name": "Human_group_actions", "confidence": 0.69}, {"start_time": 12.5, "end_time": 15.0, "name": "Human_group_actions", "confidence": 0.67}, {"start_time": 17.5, "end_time": 18.5, "name": "Crowd", "confidence": 0.62}, {"start_time": 17.5, "end_time": 18.5, "name": "Human_group_actions", "confidence": 0.75}], "num_detections": 5, "detected_classes": ["Crowd", "Human_group_actions"]}