{"detections": [{"start_time": 0.0, "end_time": 1.5, "name": "Bus", "confidence": 0.38}, {"start_time": 0.0, "end_time": 1.0, "name": "Motor_vehicle_(road)", "confidence": 0.88}, {"start_time": 0.0, "end_time": 1.0, "name": "Truck", "confidence": 0.31}, {"start_time": 0.0, "end_time": 1.0, "name": "Vehicle", "confidence": 0.98}, {"start_time": 3.0, "end_time": 6.0, "name": "Vehicle", "confidence": 0.91}, {"start_time": 8.0, "end_time": 10.0, "name": "Bird", "confidence": 0.79}, {"start_time": 8.0, "end_time": 8.5, "name": "Bus", "confidence": 0.34}], "num_detections": 7, "detected_classes": ["Bird", "Truck", "Motor_vehicle_(road)", "Bus", "Vehicle"]}