{"detections": [{"start_time": 0.0, "end_time": 5.0, "name": "Animal", "confidence": 0.89}, {"start_time": 1.0, "end_time": 3.5, "name": "Wild_animals", "confidence": 0.82}, {"start_time": 1.5, "end_time": 4.0, "name": "Bird", "confidence": 0.78}, {"start_time": 12.5, "end_time": 14.0, "name": "Bird", "confidence": 0.62}, {"start_time": 13.0, "end_time": 14.5, "name": "Animal", "confidence": 0.79}, {"start_time": 18.0, "end_time": 19.0, "name": "Livestock_and_farm_animals_and_working_animals", "confidence": 0.6}, {"start_time": 19.5, "end_time": 21.5, "name": "Animal", "confidence": 0.79}, {"start_time": 22.5, "end_time": 23.0, "name": "Animal", "confidence": 0.81}, {"start_time": 23.5, "end_time": 24.5, "name": "Animal", "confidence": 0.81}], "num_detections": 9, "detected_classes": ["Livestock_and_farm_animals_and_working_animals", "Wild_animals", "Animal", "Bird"]}