{"detections": [{"start_time": 0.0, "end_time": 0.5, "name": "Motor_vehicle_(road)", "confidence": 0.69}, {"start_time": 0.0, "end_time": 2.0, "name": "Motorcycle", "confidence": 0.7}, {"start_time": 0.0, "end_time": 6.5, "name": "Vehicle", "confidence": 0.97}, {"start_time": 1.0, "end_time": 4.5, "name": "Motor_vehicle_(road)", "confidence": 0.65}, {"start_time": 8.5, "end_time": 13.0, "name": "Vehicle", "confidence": 0.89}, {"start_time": 9.0, "end_time": 13.5, "name": "Motor_vehicle_(road)", "confidence": 0.78}, {"start_time": 9.5, "end_time": 11.5, "name": "Truck", "confidence": 0.18}, {"start_time": 11.5, "end_time": 13.0, "name": "Motorcycle", "confidence": 0.51}, {"start_time": 15.0, "end_time": 20.5, "name": "Vehicle", "confidence": 0.91}, {"start_time": 16.0, "end_time": 18.0, "name": "Car", "confidence": 0.42}, {"start_time": 16.0, "end_time": 18.0, "name": "Car_passing_by", "confidence": 0.37}, {"start_time": 16.0, "end_time": 21.0, "name": "Motor_vehicle_(road)", "confidence": 0.89}], "num_detections": 12, "detected_classes": ["Car", "Truck", "Motor_vehicle_(road)", "Car_passing_by", "Vehicle", "Motorcycle"]}