{"detections": [{"start_time": 0.0, "end_time": 1.0, "name": "Boat_and_Water_vehicle", "confidence": 0.19}, {"start_time": 25.0, "end_time": 26.0, "name": "Vehicle", "confidence": 0.96}, {"start_time": 25.5, "end_time": 27.0, "name": "Bus", "confidence": 0.4}, {"start_time": 26.5, "end_time": 28.5, "name": "Boat_and_Water_vehicle", "confidence": 0.38}, {"start_time": 27.5, "end_time": 28.5, "name": "Bus", "confidence": 0.51}], "num_detections": 5, "detected_classes": ["Boat_and_Water_vehicle", "Bus", "Vehicle"]}