{"detections": [{"start_time": 0.0, "end_time": 2.5, "name": "Animal", "confidence": 0.9}, {"start_time": 0.0, "end_time": 3.0, "name": "Bark", "confidence": 0.8}, {"start_time": 0.0, "end_time": 2.5, "name": "Dog", "confidence": 0.78}, {"start_time": 0.0, "end_time": 2.5, "name": "Domestic_animals_and_pets", "confidence": 0.88}, {"start_time": 2.0, "end_time": 3.0, "name": "Growling", "confidence": 0.32}, {"start_time": 4.5, "end_time": 8.5, "name": "Dog", "confidence": 0.74}, {"start_time": 4.5, "end_time": 8.5, "name": "Domestic_animals_and_pets", "confidence": 0.85}, {"start_time": 6.0, "end_time": 8.5, "name": "Animal", "confidence": 0.93}, {"start_time": 6.0, "end_time": 8.5, "name": "Bark", "confidence": 0.64}, {"start_time": 7.0, "end_time": 8.5, "name": "Growling", "confidence": 0.37}, {"start_time": 10.5, "end_time": 17.5, "name": "Bark", "confidence": 0.6}, {"start_time": 10.5, "end_time": 17.5, "name": "Domestic_animals_and_pets", "confidence": 0.83}, {"start_time": 11.0, "end_time": 17.5, "name": "Animal", "confidence": 0.92}, {"start_time": 11.0, "end_time": 20.5, "name": "Dog", "confidence": 0.84}, {"start_time": 18.0, "end_time": 20.5, "name": "Animal", "confidence": 0.83}, {"start_time": 18.0, "end_time": 20.5, "name": "Bark", "confidence": 0.82}, {"start_time": 18.0, "end_time": 20.5, "name": "Domestic_animals_and_pets", "confidence": 0.8}, {"start_time": 19.5, "end_time": 20.5, "name": "Growling", "confidence": 0.55}], "num_detections": 18, "detected_classes": ["Dog", "Growling", "Bark", "Domestic_animals_and_pets", "Animal"]}