{"detections": [{"start_time": 0.0, "end_time": 3.5, "name": "Animal", "confidence": 0.9}, {"start_time": 0.0, "end_time": 3.5, "name": "Bark", "confidence": 0.62}, {"start_time": 0.0, "end_time": 3.5, "name": "Dog", "confidence": 0.81}, {"start_time": 0.0, "end_time": 3.5, "name": "Domestic_animals_and_pets", "confidence": 0.75}, {"start_time": 4.5, "end_time": 7.5, "name": "Animal", "confidence": 0.97}, {"start_time": 4.5, "end_time": 7.5, "name": "Bark", "confidence": 0.86}, {"start_time": 4.5, "end_time": 7.5, "name": "Dog", "confidence": 0.97}, {"start_time": 4.5, "end_time": 7.5, "name": "Domestic_animals_and_pets", "confidence": 0.96}, {"start_time": 8.5, "end_time": 9.5, "name": "Animal", "confidence": 0.98}, {"start_time": 8.5, "end_time": 9.5, "name": "Bark", "confidence": 0.89}, {"start_time": 8.5, "end_time": 10.0, "name": "Dog", "confidence": 0.95}, {"start_time": 8.5, "end_time": 9.5, "name": "Domestic_animals_and_pets", "confidence": 0.91}, {"start_time": 11.0, "end_time": 14.5, "name": "Bark", "confidence": 0.81}, {"start_time": 11.0, "end_time": 18.0, "name": "Dog", "confidence": 0.56}, {"start_time": 11.5, "end_time": 18.0, "name": "Animal", "confidence": 0.85}, {"start_time": 11.5, "end_time": 18.0, "name": "Domestic_animals_and_pets", "confidence": 0.82}, {"start_time": 15.0, "end_time": 16.5, "name": "Livestock_and_farm_animals_and_working_animals", "confidence": 0.38}, {"start_time": 16.0, "end_time": 18.0, "name": "Bark", "confidence": 0.64}], "num_detections": 18, "detected_classes": ["Livestock_and_farm_animals_and_working_animals", "Domestic_animals_and_pets", "Bark", "Dog", "Animal"]}