{"detections": [{"start_time": 0.0, "end_time": 0.5, "name": "Knock", "confidence": 0.53}, {"start_time": 0.0, "end_time": 1.0, "name": "Tools", "confidence": 0.45}, {"start_time": 4.0, "end_time": 5.0, "name": "Domestic_sounds_and_home_sounds", "confidence": 0.67}, {"start_time": 4.0, "end_time": 5.0, "name": "Door", "confidence": 0.92}, {"start_time": 4.0, "end_time": 5.0, "name": "Knock", "confidence": 0.87}, {"start_time": 5.5, "end_time": 7.0, "name": "Hammer", "confidence": 0.39}, {"start_time": 5.5, "end_time": 12.0, "name": "Tools", "confidence": 0.66}, {"start_time": 6.0, "end_time": 7.5, "name": "Door", "confidence": 0.69}, {"start_time": 6.0, "end_time": 7.5, "name": "Knock", "confidence": 0.62}, {"start_time": 8.0, "end_time": 12.0, "name": "Hammer", "confidence": 0.44}, {"start_time": 11.0, "end_time": 12.0, "name": "Door", "confidence": 0.45}, {"start_time": 11.0, "end_time": 12.0, "name": "Knock", "confidence": 0.59}, {"start_time": 13.0, "end_time": 13.5, "name": "Tools", "confidence": 0.51}], "num_detections": 13, "detected_classes": ["Domestic_sounds_and_home_sounds", "Door", "Knock", "Hammer", "Tools"]}