{"detections": [{"start_time": 0.0, "end_time": 1.5, "name": "Drip", "confidence": 0.41}, {"start_time": 0.0, "end_time": 1.5, "name": "Liquid", "confidence": 0.95}, {"start_time": 4.5, "end_time": 7.5, "name": "Liquid", "confidence": 0.74}, {"start_time": 6.0, "end_time": 7.5, "name": "Drip", "confidence": 0.4}, {"start_time": 13.0, "end_time": 14.5, "name": "Liquid", "confidence": 0.68}, {"start_time": 19.0, "end_time": 27.0, "name": "Liquid", "confidence": 0.68}, {"start_time": 21.5, "end_time": 24.5, "name": "Drip", "confidence": 0.51}, {"start_time": 26.5, "end_time": 27.0, "name": "Tap", "confidence": 0.47}], "num_detections": 8, "detected_classes": ["Liquid", "Tap", "Drip"]}