{"detections": [{"start_time": 0.0, "end_time": 0.5, "name": "Alarm", "confidence": 0.99}, {"start_time": 0.0, "end_time": 0.5, "name": "Motor_vehicle_(road)", "confidence": 0.94}, {"start_time": 3.5, "end_time": 6.0, "name": "Alarm", "confidence": 0.99}, {"start_time": 3.5, "end_time": 6.5, "name": "Motor_vehicle_(road)", "confidence": 0.93}, {"start_time": 5.0, "end_time": 6.0, "name": "Vehicle", "confidence": 0.99}], "num_detections": 5, "detected_classes": ["Alarm", "Vehicle", "Motor_vehicle_(road)"]}