{"detections": [{"start_time": 1.0, "end_time": 5.0, "name": "Keyboard_(musical)", "confidence": 0.48}, {"start_time": 3.0, "end_time": 6.0, "name": "Music", "confidence": 0.97}, {"start_time": 3.0, "end_time": 6.0, "name": "Musical_instrument", "confidence": 0.97}, {"start_time": 7.0, "end_time": 10.5, "name": "Keyboard_(musical)", "confidence": 0.4}, {"start_time": 8.5, "end_time": 10.5, "name": "Music", "confidence": 0.97}, {"start_time": 8.5, "end_time": 10.5, "name": "Musical_instrument", "confidence": 0.97}], "num_detections": 6, "detected_classes": ["Keyboard_(musical)", "Music", "Musical_instrument"]}