{"detections": [{"start_time": 0.0, "end_time": 0.5, "name": "Bell", "confidence": 0.94}, {"start_time": 0.0, "end_time": 0.5, "name": "Chime", "confidence": 0.75}, {"start_time": 0.0, "end_time": 0.5, "name": "Wind_chime", "confidence": 0.31}, {"start_time": 1.0, "end_time": 12.5, "name": "Mechanisms", "confidence": 0.43}, {"start_time": 2.0, "end_time": 3.0, "name": "Chime", "confidence": 0.71}, {"start_time": 2.5, "end_time": 4.0, "name": "Bell", "confidence": 0.69}, {"start_time": 6.0, "end_time": 7.0, "name": "Bell", "confidence": 0.72}, {"start_time": 6.0, "end_time": 7.0, "name": "Chime", "confidence": 0.72}, {"start_time": 6.0, "end_time": 7.0, "name": "Wind_chime", "confidence": 0.41}, {"start_time": 8.5, "end_time": 11.5, "name": "Chime", "confidence": 0.85}, {"start_time": 8.5, "end_time": 9.5, "name": "Wind_chime", "confidence": 0.38}, {"start_time": 9.0, "end_time": 11.0, "name": "Bell", "confidence": 0.69}, {"start_time": 13.5, "end_time": 14.5, "name": "Chime", "confidence": 0.78}, {"start_time": 13.5, "end_time": 14.5, "name": "Wind_chime", "confidence": 0.28}, {"start_time": 14.0, "end_time": 18.5, "name": "Mechanisms", "confidence": 0.54}, {"start_time": 18.0, "end_time": 19.5, "name": "Chime", "confidence": 0.66}, {"start_time": 18.5, "end_time": 19.0, "name": "Wind_chime", "confidence": 0.29}, {"start_time": 19.5, "end_time": 20.0, "name": "Bell", "confidence": 0.63}, {"start_time": 20.0, "end_time": 22.0, "name": "Mechanisms", "confidence": 0.47}, {"start_time": 23.0, "end_time": 25.5, "name": "Mechanisms", "confidence": 0.44}], "num_detections": 20, "detected_classes": ["Mechanisms", "Bell", "Wind_chime", "Chime"]}