{"detections": [{"start_time": 0.0, "end_time": 4.0, "name": "Clapping", "confidence": 0.71}, {"start_time": 0.0, "end_time": 4.0, "name": "Hands", "confidence": 0.69}, {"start_time": 2.0, "end_time": 3.5, "name": "Human_group_actions", "confidence": 0.69}, {"start_time": 5.0, "end_time": 8.0, "name": "Clapping", "confidence": 0.67}, {"start_time": 5.0, "end_time": 8.0, "name": "Hands", "confidence": 0.64}, {"start_time": 5.5, "end_time": 7.5, "name": "Human_group_actions", "confidence": 0.62}], "num_detections": 6, "detected_classes": ["Clapping", "Human_group_actions", "Hands"]}